py2cpp/__init__.py
py2cpp/cli.py
py2cpp/setting.py
py2cpp/core/__init__.py
py2cpp/core/compiler.py
py2cpp/core/jit.py
py2cpp/utils/__init__.py
py2cpp/utils/code.py
py2cpp/utils/header.py
py2cpp/utils/parse.py
py2cpp/utils/type.py
py2cpp-1.7.1.dist-info/LICENSE
py2cpp-1.7.1.dist-info/METADATA
py2cpp-1.7.1.dist-info/WHEEL
py2cpp-1.7.1.dist-info/entry_points.txt
py2cpp-1.7.1.dist-info/top_level.txt
py2cpp-1.7.1.dist-info/RECORD
