Metadata-Version: 2.1
Name: py2cpp
Version: 1.7.1
Summary: A Python-to-C++ translator.
Author: typeulli
Requires-Python: >=3.10
License-File: LICENSE
Requires-Dist: click >=8.1.7
Requires-Dist: mypy >=1.8.0
